MANIFEST.in
README.rst
setup.py
notify_run/__init__.py
notify_run/cli.py
notify_run/keras.py
notify_run.egg-info/PKG-INFO
notify_run.egg-info/SOURCES.txt
notify_run.egg-info/dependency_links.txt
notify_run.egg-info/entry_points.txt
notify_run.egg-info/requires.txt
notify_run.egg-info/top_level.txt
screenshots/notebook.png
screenshots/register.png