Metadata-Version: 1.2
Name: notify-run
Version: 0.0.11
Summary: Client for notify.run notifications.
Home-page: https://notify.run/
Author: Paul Butler
Author-email: notify@paulbutler.org
License: UNKNOWN
Platform: UNKNOWN
Requires-Python: >=2.7
